py_cmdtabs/__init__.py
py_cmdtabs/cli_manager.py
py_cmdtabs/cmdtabs.py
py_cmdtabs-1.1.0.dist-info/LICENSE.txt
py_cmdtabs-1.1.0.dist-info/METADATA
py_cmdtabs-1.1.0.dist-info/WHEEL
py_cmdtabs-1.1.0.dist-info/entry_points.txt
py_cmdtabs-1.1.0.dist-info/top_level.txt
py_cmdtabs-1.1.0.dist-info/RECORD
